{"permissions":[{"permissionName":"9c2bc39b-13ff-4b1b-976b-56f01f2cd9d9","displayName":"Admin","id":"9c2bc39b-13ff-4b1b-976b-56f01f2cd9d9","description":"All permissions.","tags":[],"subPermissions":["ui-agreements.agreements.delete","ui-agreements.agreements.edit","ui-agreements.resources.edit","ui-agreements.platforms.edit","ui-agreements.agreements.view","ui-agreements.resources.view","ui-agreements.platforms.view","ui-plugin-bursar-export.bursar-exports.all","ui-checkin.all","ui-checkout.all","ui-checkout.circulation","ui-checkout.viewFeeFines","ui-checkout.viewLoans","ui-checkout.viewRequests","ui-circulation-log.log-event.all","ui-courses.add-edit-items","ui-courses.maintain-items","ui-courses.all","ui-courses.read-all","ui-courses.read-add-edit","module.data-import.enabled","ui-eholdings.titles-packages.create-delete","ui-eholdings.records.edit","ui-eholdings.package-title.select-unselect","ui-eholdings.app.enabled","ui-eholdings.costperuse.view","ui-erm-comparisons.jobs.edit","ui-erm-comparisons.jobs.delete","ui-erm-comparisons.jobs.view","ui-erm-usage.harvester.all","ui-erm-usage.harvester.view","ui-erm-usage.all","ui-erm-usage.view-create","ui-erm-usage.view-edit","ui-erm-usage.view","ui-erm-usage.view-create-edit","ui-erm-usage.view-create-edit-delete","ui-export-manager.export-manager.all","ui-plugin-create-inventory-records.create","ui-users.feefineactions","ui-users.accounts","ui-users.manual_charge","ui-users.manual_pay","ui-users.manual_waive","ui-finance.acq.unit.assignment.assign","ui-finance.allocations.create","ui-finance.transfers.create","ui-finance.ledger.rollover","ui-finance.acq.unit.assignment.manage","ui-finance.manually-release-encumbrances","ui-finance.fiscal-year.view","ui-finance.fund-budget.view","ui-finance.group.view","ui-finance.ledger.view","ui-finance.fiscal-year.edit","ui-finance.fund-budget.edit","ui-finance.group.edit","ui-finance.ledger.edit","ui-finance.fiscal-year.create","ui-finance.fund-budget.create","ui-finance.group.create","ui-finance.ledger.create","ui-finance.fiscal-year.delete","ui-finance.fund-budget.delete","ui-finance.group.delete","ui-finance.ledger.delete","ui-plugin-find-agreement.search","ui-plugin-find-eresource.search","ui-plugin-find-license.search","ui-inventory.all-permissions.TEMPORARY","ui-inventory.single-record-import","ui-inventory.items.mark-in-process-non-requestable","ui-inventory.items.mark-intellectual-item","ui-inventory.items.mark-long-missing","ui-inventory.items.mark-restricted","ui-inventory.items.mark-unavailable","ui-inventory.items.mark-unknown","ui-inventory.items.mark-items-withdrawn","ui-inventory.holdings.move","ui-inventory.item.move","ui-inventory.instance.view-staff-suppressed-records","ui-inventory.instance.view","ui-inventory.holdings.create","ui-inventory.instance.create","ui-inventory.item.create","ui-inventory.holdings.edit","ui-inventory.instance.edit","ui-inventory.item.edit","ui-inventory.holdings.delete","ui-inventory.item.delete","ui-inventory.item.markasmissing","ui-invoice.approve","ui-invoice.acq.unit.assignment.assign","ui-invoice.invoice.edit","ui-invoice.invoice.view","ui-invoice.invoice.create","ui-invoice.invoice.delete","ui-invoice.batchVoucher.download","ui-invoice.acq.unit.assignment.manage","ui-invoice.pay","ui-licenses.licenses.delete","ui-licenses.licenses.edit","ui-licenses.licenses.view","ui-local-kb-admin.jobs.edit","ui-local-kb-admin.jobs.delete","ui-local-kb-admin.proxyServer.manage","ui-local-kb-admin.kbs.manage","ui-local-kb-admin.jobs.view","login-saml.all","ui-notes.item.assign-unassign","ui-notes.item.create","ui-notes.item.delete","ui-notes.item.edit","ui-notes.item.view","ui-orders.acq.unit.assignment.assign","ui-orders.order-lines.create","ui-orders.order.create","ui-orders.order-lines.delete","ui-orders.order-lines.edit","ui-orders.order.edit","ui-orders.order.exportCSV","ui-orders.acq.unit.assignment.manage","ui-orders.order.delete","ui-orders.order.reopen","ui-orders.order.unopen","ui-orders.order.updateEncumbrances","ui-orders.order-lines.view","ui-orders.order.view","ui-organizations.acqUnits.assign","ui-organizations.creds.view","ui-organizations.creds.manage","ui-organizations.acqUnits.manage","ui-organizations.view","ui-organizations.edit","ui-organizations.create","ui-organizations.delete","ui-quick-marc.quick-marc-editor.duplicate","ui-quick-marc.quick-marc-editor.all","ui-receiving.view","ui-receiving.edit","ui-receiving.create","ui-receiving.delete","ui-remote-storage.settings.remote-storages.all","ui-requests.all","ui-requests.moveRequest","ui-requests.reorderQueue","ui-requests.view","ui-requests.create","ui-requests.edit","login-saml.configuration.put","login-saml.configuration.get","ui-search.codexsearch","ui-acquisition-units.settings.all","ui-agreements.generalSettings.manage","ui-agreements.supplementaryProperties.manage","ui-agreements.picklists.manage","ui-calendar.edit","ui-calendar.all","ui-calendar.view","ui-circulation.settings.cancellation-reasons","ui-circulation.settings.circulation-rules","ui-circulation.settings.fixed-due-date-schedules","ui-circulation.settings.loan-policies","ui-circulation.settings.lost-item-fees-policies","ui-circulation.settings.notice-policies","ui-circulation.settings.other-settings","ui-circulation.settings.overdue-fines-policies","ui-circulation.settings.notice-templates","ui-circulation.settings.request-policies","ui-circulation.settings.staff-slips","ui-circulation.settings.loan-history","ui-courses.maintain-settings","settings.data-import.enabled","ui-data-export.settings.enabled","ui-developer.settings.passwd","ui-developer.settings.dependencies","ui-developer.settings.okapiConfiguration","ui-developer.settings.okapiQuery","ui-developer.settings.configuration","ui-developer.settings.hotkeys","ui-developer.settings.token","ui-developer.settings.perms","ui-developer.settings.locale","ui-eholdings.settings.assignedUser","ui-eholdings.settings.access-types.create-edit","ui-eholdings.settings.kb","ui-eholdings.settings.access-types.all","ui-eholdings.settings.custom-labels.all","ui-eholdings.settings.kb.delete","ui-eholdings.settings.access-types.view","ui-eholdings.settings.custom-labels.view","ui-eholdings.settings.root-proxy","ui-eholdings.settings.usage-consolidation.create-edit","ui-eholdings.settings.enabled","ui-eholdings.settings.usage-consolidation.view","ui-erm-usage.generalSettings.manage","ui-finance.settings.all","ui-inventory.settings.single-record-import","ui-inventory.settings.hrid-handling","ui-inventory.settings.alternative-title-types","ui-inventory.settings.call-number-types","ui-inventory.settings.classification-types","ui-inventory.settings.contributor-types","ui-inventory.settings.instance-formats","ui-inventory.settings.holdings-note-types","ui-inventory.settings.holdings-sources","ui-inventory.settings.holdings-types","ui-inventory.settings.ill-policies","ui-inventory.settings.instance-note-types","ui-inventory.settings.instance-statuses","ui-inventory.settings.item-note-types","ui-inventory.settings.loantypes","ui-inventory.settings.modes-of-issuance","ui-inventory.settings.instance-types","ui-inventory.settings.materialtypes","ui-inventory.settings.nature-of-content-terms","ui-inventory.settings.identifier-types","ui-inventory.settings.statistical-code-types","ui-inventory.settings.statistical-codes","ui-inventory.settings.electronic-access-relationships","ui-inventory.settings.fast-add","ui-inventory.settings.list.view","ui-invoice.settings.all","ui-licenses.terms.manage","ui-licenses.picklists.manage","ui-myprofile.settings.change-password","settings.notes.enabled","ui-oai-pmh.edit","ui-oai-pmh.view","ui-orders.settings.view","ui-orders.settings.all","ui-orders.settings.order-templates.view","ui-orders.settings.order-templates.edit","ui-orders.settings.order-templates.create","ui-orders.settings.order-templates.delete","ui-organizations.settings","ui-receiving.settings","ui-tags.settings","ui-tenant-settings.settings.servicepoints","ui-tenant-settings.settings.location","ui-tenant-settings.settings.locale","ui-tenant-settings.settings.key-bindings","ui-tenant-settings.settings.plugins","ui-tenant-settings.settings.sso","ui-tenant-settings.settings.addresses","ui-tenant-settings.settings.enabled","ui-users.settings.addresstypes","ui-users.settings.feefines.all","ui-users.settings.comments","ui-users.settings.feefines","ui-users.settings.owners","ui-users.settings.conditions","ui-users.settings.limits","ui-users.settings.patron-block-templates","ui-users.settings.usergroups","ui-users.settings.payments","ui-users.settings.profilePictures","ui-users.settings.permsets","ui-users.settings.refunds","ui-users.settings.transfers","ui-users.settings.transfertypes","ui-users.settings.waives","ui-users.settings.customfields.edit","ui-users.settings.customfields.all","ui-users.settings.customfields.view","ui-users.settings.departments.create.edit.view","ui-users.settings.departments.all","ui-users.settings.departments.view","ui-tags.view","ui-tags.all","module.search.enabled","ui-data-export.app.enabled","user-import.all","ui-users.overrideItemBlock","ui-users.overridePatronBlock","ui-users.editperms","ui-users.edituserservicepoints","ui-users.create","ui-users.feesfines.actions.all","ui-users.patron_blocks","ui-users.editproxies","ui-users.edit","ui-users.viewperms","ui-users.viewproxies","ui-users.viewuserservicepoints","ui-users.view","ui-users.manualProcessRefundsReport","ui-users.reset.password","ui-users.loans.anonymize","ui-users.loans.change-due-date","ui-users.loans.claim-item-returned","ui-users.loans.declare-item-lost","ui-users.loans.declare-claimed-returned-item-as-missing","ui-users.loans.renew","ui-users.loans.renew-override","ui-users.loans.view","ui-users.loans.all","ui-users.requests.all"],"mutable":true,"visible":true},{"permissionName":"27f7bf8b-c79d-48a8-82bb-ae370cf52396","displayName":"E-resources 5 (Staff)","id":"27f7bf8b-c79d-48a8-82bb-ae370cf52396","tags":[],"subPermissions":["ui-agreements.agreements.edit","ui-agreements.resources.edit","ui-agreements.platforms.edit","ui-agreements.agreements.view","ui-agreements.resources.view","ui-agreements.platforms.view","ui-eholdings.records.edit","ui-eholdings.package-title.select-unselect","ui-eholdings.app.enabled","ui-eholdings.costperuse.view","ui-erm-comparisons.jobs.edit","ui-erm-comparisons.jobs.view","ui-erm-usage.harvester.view","ui-erm-usage.view-create-edit","ui-plugin-find-agreement.search","ui-plugin-find-license.search","ui-licenses.licenses.edit","ui-licenses.licenses.view","ui-local-kb-admin.jobs.edit","ui-local-kb-admin.jobs.view","ui-organizations.acqUnits.assign","ui-organizations.creds.view","ui-organizations.create"],"mutable":true,"visible":true},{"permissionName":"724681b5-fd81-4937-9054-b7765485baf5","displayName":"Access 2 (Casual/hourly I)","id":"724681b5-fd81-4937-9054-b7765485baf5","description":"Permissions for staff working in access-related function (e.g., Stacks hourlies)","tags":[],"subPermissions":["ui-checkin.all"],"mutable":true,"visible":true},{"permissionName":"112a8d5d-8775-4586-b18f-8ab8a33859ac","displayName":"Access 3 (Casual/hourly II)","id":"112a8d5d-8775-4586-b18f-8ab8a33859ac","description":"Permissions for staff working in access-related function (e.g., students)","tags":[],"subPermissions":["ui-checkin.all","ui-checkout.circulation","ui-checkout.viewFeeFines","ui-checkout.viewLoans","ui-checkout.viewRequests","ui-courses.read-all","ui-inventory.instance.view","ui-requests.view","ui-users.view","ui-users.loans.view","ui-users.requests.all"],"mutable":true,"visible":true},{"permissionName":"770b9731-42b3-47e5-a4f2-8add5518a8f4","displayName":"Access 4 (Staff I)","id":"770b9731-42b3-47e5-a4f2-8add5518a8f4","description":"Permissions for staff working in access-related functions (circulation staff, ILL staff)","tags":[],"subPermissions":["ui-checkin.all","ui-checkout.all","ui-checkout.circulation","ui-checkout.viewFeeFines","ui-checkout.viewLoans","ui-checkout.viewRequests","ui-circulation-log.log-event.all","ui-courses.read-all","ui-users.manual_charge","ui-users.manual_pay","ui-users.manual_waive","ui-inventory.items.mark-long-missing","ui-inventory.items.mark-restricted","ui-inventory.items.mark-unavailable","ui-requests.all","ui-calendar.view","ui-users.overrideItemBlock","ui-users.overridePatronBlock","ui-users.create","ui-users.feesfines.actions.all","ui-users.patron_blocks","ui-users.editproxies","ui-users.edit","ui-users.viewperms","ui-users.viewproxies","ui-users.viewuserservicepoints","ui-users.view","ui-users.reset.password","ui-users.loans.change-due-date","ui-users.loans.claim-item-returned","ui-users.loans.declare-item-lost","ui-users.loans.declare-claimed-returned-item-as-missing","ui-users.loans.renew","ui-users.loans.view","ui-users.requests.all"],"mutable":true,"visible":true},{"permissionName":"5cf226a4-fc40-46a5-b97d-cd4d3fea483a","displayName":"Access 7 (Admin)","id":"5cf226a4-fc40-46a5-b97d-cd4d3fea483a","description":"Administrator-level permissions for a librarian, head of department, assistant head of department. Staff who are able to make policy setting and implements access to staff based on those decisions.","tags":[],"subPermissions":["ui-checkin.all","ui-checkout.all","ui-checkout.circulation","ui-checkout.viewFeeFines","ui-checkout.viewLoans","ui-checkout.viewRequests","ui-circulation-log.log-event.all","ui-courses.all","ui-plugin-create-inventory-records.create","ui-users.accounts","ui-users.manual_charge","ui-users.manual_pay","ui-users.manual_waive","ui-inventory.items.mark-long-missing","ui-inventory.items.mark-restricted","ui-inventory.items.mark-unavailable","ui-inventory.items.mark-unknown","ui-inventory.instance.view-staff-suppressed-records","ui-inventory.instance.view","ui-orders.order-lines.view","ui-orders.order.view","ui-requests.all","ui-calendar.edit","ui-calendar.all","ui-calendar.view","ui-circulation.settings.cancellation-reasons","ui-circulation.settings.circulation-rules","ui-circulation.settings.fixed-due-date-schedules","ui-circulation.settings.loan-policies","ui-circulation.settings.lost-item-fees-policies","ui-circulation.settings.notice-policies","ui-circulation.settings.request-policies","ui-circulation.settings.staff-slips","ui-circulation.settings.loan-history","ui-courses.maintain-settings","ui-users.settings.addresstypes","ui-users.settings.feefines.all","ui-users.settings.comments","ui-users.settings.feefines","ui-users.settings.owners","ui-users.settings.conditions","ui-users.settings.limits","ui-users.settings.patron-block-templates","ui-users.settings.usergroups","ui-users.settings.payments","ui-users.settings.refunds","ui-users.settings.waives","ui-users.overrideItemBlock","ui-users.overridePatronBlock","ui-users.editperms","ui-users.edituserservicepoints","ui-users.create","ui-users.feesfines.actions.all","ui-users.patron_blocks","ui-users.editproxies","ui-users.edit","ui-users.viewperms","ui-users.viewproxies","ui-users.viewuserservicepoints","ui-users.view","ui-users.reset.password","ui-users.loans.anonymize","ui-users.loans.change-due-date","ui-users.loans.claim-item-returned","ui-users.loans.declare-item-lost","ui-users.loans.declare-claimed-returned-item-as-missing","ui-users.loans.renew","ui-users.loans.renew-override","ui-users.loans.view","ui-users.loans.all","ui-users.requests.all"],"mutable":true,"visible":true},{"permissionName":"acc30999-3f7d-49a0-9147-a5c700ea8e07","displayName":"Acquisitions 6 (Manager)","id":"acc30999-3f7d-49a0-9147-a5c700ea8e07","tags":[],"subPermissions":["ui-finance.fiscal-year.view","ui-finance.fund-budget.view","ui-finance.group.view","ui-finance.ledger.view","ui-invoice.invoice.view","ui-notes.item.assign-unassign","ui-notes.item.create","ui-notes.item.delete","ui-notes.item.edit","ui-notes.item.view","ui-orders.acq.unit.assignment.assign","ui-orders.order-lines.create","ui-orders.order.create","ui-orders.order-lines.delete","ui-orders.order-lines.edit","ui-orders.order.edit","ui-orders.order.exportCSV","ui-orders.order.delete","ui-orders.order.reopen","ui-orders.order.unopen","ui-orders.order.updateEncumbrances","ui-orders.order-lines.view","ui-orders.order.view","ui-organizations.creds.manage","ui-organizations.view","ui-receiving.create","ui-receiving.delete","ui-tags.all"],"mutable":true,"visible":true},{"permissionName":"a19d7edd-220e-4f8e-a2c4-b9e8d2289713","displayName":"Acquisitions Payments 6 (Manager)","id":"a19d7edd-220e-4f8e-a2c4-b9e8d2289713","tags":[],"subPermissions":["ui-finance.transfers.create","ui-finance.fiscal-year.view","ui-finance.group.view","ui-finance.ledger.view","ui-finance.fund-budget.edit","ui-invoice.approve","ui-invoice.acq.unit.assignment.assign","ui-invoice.invoice.create","ui-invoice.invoice.delete","ui-invoice.batchVoucher.download","ui-invoice.pay","ui-organizations.acqUnits.assign","ui-organizations.creds.manage","ui-organizations.create","ui-organizations.delete"],"mutable":true,"visible":true},{"permissionName":"98a37906-1d27-4b97-8302-a10d673b2cdc","displayName":"Acquisitions 5 (Staff)","id":"98a37906-1d27-4b97-8302-a10d673b2cdc","tags":[],"subPermissions":["ui-finance.fiscal-year.view","ui-finance.fund-budget.view","ui-finance.group.view","ui-finance.ledger.view","ui-invoice.invoice.view","ui-notes.item.create","ui-notes.item.delete","ui-notes.item.edit","ui-notes.item.view","ui-orders.acq.unit.assignment.assign","ui-orders.order-lines.create","ui-orders.order.create","ui-orders.order-lines.edit","ui-orders.order.edit","ui-orders.order.exportCSV","ui-orders.order.reopen","ui-orders.order.unopen","ui-orders.order.updateEncumbrances","ui-orders.order-lines.view","ui-orders.order.view","ui-organizations.creds.view","ui-organizations.view","ui-receiving.create","ui-tags.all"],"mutable":true,"visible":true},{"permissionName":"8c9135a7-d1af-452f-bdcb-d63106ecdf95","displayName":"Access 6 (Manager)","id":"8c9135a7-d1af-452f-bdcb-d63106ecdf95","description":"Permissions for management-level staff who can perform more work than general staff, but less than Admin-level staff. These can include Operations Managers, Student Supervisors, etc.","tags":[],"subPermissions":["ui-checkin.all","ui-checkout.all","ui-checkout.viewFeeFines","ui-checkout.viewLoans","ui-checkout.viewRequests","ui-circulation-log.log-event.all","ui-courses.all","ui-plugin-create-inventory-records.create","ui-users.accounts","ui-users.manual_charge","ui-users.manual_pay","ui-users.manual_waive","ui-inventory.items.mark-long-missing","ui-inventory.items.mark-restricted","ui-inventory.items.mark-unavailable","ui-inventory.instance.view-staff-suppressed-records","ui-inventory.instance.view","ui-orders.order-lines.view","ui-orders.order.view","ui-requests.all","ui-calendar.view","ui-users.overrideItemBlock","ui-users.overridePatronBlock","ui-users.editperms","ui-users.edituserservicepoints","ui-users.create","ui-users.feesfines.actions.all","ui-users.patron_blocks","ui-users.editproxies","ui-users.edit","ui-users.viewperms","ui-users.viewproxies","ui-users.viewuserservicepoints","ui-users.view","ui-users.reset.password","ui-users.loans.anonymize","ui-users.loans.change-due-date","ui-users.loans.claim-item-returned","ui-users.loans.declare-item-lost","ui-users.loans.declare-claimed-returned-item-as-missing","ui-users.loans.renew","ui-users.loans.renew-override","ui-users.loans.view","ui-users.loans.all","ui-users.requests.all"],"mutable":true,"visible":true},{"permissionName":"2a818fc4-db77-4552-8dca-16fba99de41f","displayName":"Acquisitions Payments 7 (Admin)","id":"2a818fc4-db77-4552-8dca-16fba99de41f","tags":[],"subPermissions":["ui-finance.acq.unit.assignment.assign","ui-finance.allocations.create","ui-finance.transfers.create","ui-finance.manually-release-encumbrances","ui-finance.fiscal-year.create","ui-finance.fund-budget.create","ui-finance.group.create","ui-finance.ledger.create","ui-invoice.approve","ui-invoice.acq.unit.assignment.assign","ui-invoice.invoice.create","ui-invoice.invoice.delete","ui-invoice.batchVoucher.download","ui-invoice.pay","ui-organizations.acqUnits.assign","ui-organizations.creds.manage","ui-organizations.create","ui-organizations.delete"],"mutable":true,"visible":true},{"permissionName":"d079940f-5fd4-459d-9a71-522a6b9b0787","displayName":"Cataloging 3 (Casual/hourly)","id":"d079940f-5fd4-459d-9a71-522a6b9b0787","tags":[],"subPermissions":["ui-plugin-create-inventory-records.create","ui-inventory.instance.view-staff-suppressed-records","ui-inventory.instance.view","ui-inventory.holdings.edit","ui-inventory.instance.edit","ui-inventory.item.edit","ui-notes.item.view","ui-quick-marc.quick-marc-editor.all","ui-tags.view"],"mutable":true,"visible":true},{"permissionName":"33a93112-afe7-439f-adc4-1cc66aa23411","displayName":"Access 1 (View only)","id":"33a93112-afe7-439f-adc4-1cc66aa23411","tags":[],"subPermissions":["ui-checkout.viewLoans","ui-checkout.viewRequests","ui-courses.read-all","ui-requests.view"],"mutable":true,"visible":true},{"permissionName":"80e1d99e-c7a6-4a76-86b7-f029097b550c","displayName":"Cataloging 1 (View only)","id":"80e1d99e-c7a6-4a76-86b7-f029097b550c","tags":[],"subPermissions":["ui-inventory.instance.view-staff-suppressed-records","ui-inventory.instance.view","ui-notes.item.view","ui-tags.view"],"mutable":true,"visible":true},{"permissionName":"0ae09bbc-1124-4b79-b965-f7eb9527f305","displayName":"Acquisitions Payments 7 (Admin)","id":"0ae09bbc-1124-4b79-b965-f7eb9527f305","tags":[],"subPermissions":["ui-finance.acq.unit.assignment.assign","ui-finance.allocations.create","ui-finance.transfers.create","ui-finance.manually-release-encumbrances","ui-finance.fiscal-year.view","ui-finance.fund-budget.view","ui-finance.group.view","ui-finance.ledger.view","ui-finance.fiscal-year.edit","ui-finance.fund-budget.edit","ui-finance.group.edit","ui-finance.ledger.edit","ui-finance.fiscal-year.create","ui-finance.fund-budget.create","ui-finance.group.create","ui-finance.ledger.create","ui-finance.fiscal-year.delete","ui-finance.fund-budget.delete","ui-finance.group.delete","ui-finance.ledger.delete","ui-finance.settings.all"],"mutable":true,"visible":true},{"permissionName":"14c817a6-8a9c-4cb4-8b0b-ae090dcdf86e","displayName":"Cataloging 6 (Manager)","id":"14c817a6-8a9c-4cb4-8b0b-ae090dcdf86e","tags":[],"subPermissions":["module.data-import.enabled","ui-plugin-create-inventory-records.create","ui-inventory.all-permissions.TEMPORARY","ui-notes.item.create","ui-notes.item.delete","ui-notes.item.edit","ui-notes.item.view","ui-quick-marc.quick-marc-editor.duplicate","ui-quick-marc.quick-marc-editor.all","ui-inventory.settings.list.view","ui-tags.all"],"mutable":true,"visible":true},{"permissionName":"cfc6d709-793a-42c3-9272-d41985b5a2b4","displayName":"E-resources 6 (Manager)","id":"cfc6d709-793a-42c3-9272-d41985b5a2b4","tags":[],"subPermissions":["ui-agreements.agreements.delete","ui-agreements.agreements.edit","ui-agreements.resources.edit","ui-agreements.platforms.edit","ui-agreements.agreements.view","ui-agreements.resources.view","ui-agreements.platforms.view","ui-eholdings.titles-packages.create-delete","ui-eholdings.records.edit","ui-eholdings.package-title.select-unselect","ui-eholdings.app.enabled","ui-eholdings.costperuse.view","ui-erm-comparisons.jobs.edit","ui-erm-comparisons.jobs.delete","ui-erm-comparisons.jobs.view","ui-erm-usage.harvester.all","ui-erm-usage.all","ui-plugin-find-agreement.search","ui-plugin-find-license.search","ui-licenses.licenses.delete","ui-licenses.licenses.edit","ui-licenses.licenses.view","ui-local-kb-admin.jobs.edit","ui-local-kb-admin.jobs.delete","ui-local-kb-admin.proxyServer.manage","ui-local-kb-admin.kbs.manage","ui-local-kb-admin.jobs.view","ui-organizations.acqUnits.assign","ui-organizations.creds.manage","ui-organizations.create","ui-organizations.delete"],"mutable":true,"visible":true},{"permissionName":"6c6f149e-becd-4211-8cea-28b909ac5dc1","displayName":"Cataloging 7 (Administrator)","id":"6c6f149e-becd-4211-8cea-28b909ac5dc1","tags":[],"subPermissions":["module.data-import.enabled","ui-export-manager.export-manager.all","ui-plugin-create-inventory-records.create","ui-inventory.all-permissions.TEMPORARY","ui-notes.item.assign-unassign","ui-notes.item.create","ui-notes.item.delete","ui-notes.item.edit","ui-notes.item.view","ui-quick-marc.quick-marc-editor.duplicate","ui-quick-marc.quick-marc-editor.all","settings.data-import.enabled","ui-data-export.settings.enabled","ui-inventory.settings.single-record-import","ui-inventory.settings.list.view","ui-users.settings.permsets","ui-tags.all"],"mutable":true,"visible":true},{"permissionName":"93bb9196-0e78-45a8-91d1-bb379c083343","displayName":"E-resources 7 (Admin)","id":"93bb9196-0e78-45a8-91d1-bb379c083343","tags":[],"subPermissions":["ui-agreements.agreements.delete","ui-agreements.agreements.edit","ui-agreements.resources.edit","ui-agreements.platforms.edit","ui-agreements.agreements.view","ui-agreements.resources.view","ui-agreements.platforms.view","ui-eholdings.titles-packages.create-delete","ui-eholdings.records.edit","ui-eholdings.package-title.select-unselect","ui-eholdings.app.enabled","ui-eholdings.costperuse.view","ui-erm-comparisons.jobs.edit","ui-erm-comparisons.jobs.delete","ui-erm-comparisons.jobs.view","ui-erm-usage.harvester.all","ui-erm-usage.all","ui-plugin-find-agreement.search","ui-plugin-find-license.search","ui-licenses.licenses.delete","ui-licenses.licenses.edit","ui-licenses.licenses.view","ui-local-kb-admin.jobs.edit","ui-local-kb-admin.jobs.delete","ui-local-kb-admin.proxyServer.manage","ui-local-kb-admin.kbs.manage","ui-local-kb-admin.jobs.view","ui-organizations.acqUnits.assign","ui-organizations.creds.manage","ui-organizations.create","ui-organizations.delete","ui-agreements.generalSettings.manage","ui-agreements.supplementaryProperties.manage","ui-agreements.picklists.manage","ui-eholdings.settings.assignedUser","ui-eholdings.settings.access-types.create-edit","ui-eholdings.settings.kb","ui-eholdings.settings.access-types.all","ui-eholdings.settings.custom-labels.all","ui-eholdings.settings.kb.delete","ui-eholdings.settings.access-types.view","ui-eholdings.settings.custom-labels.view","ui-eholdings.settings.root-proxy","ui-eholdings.settings.usage-consolidation.create-edit","ui-eholdings.settings.enabled","ui-eholdings.settings.usage-consolidation.view","ui-erm-usage.generalSettings.manage","ui-licenses.terms.manage","ui-licenses.picklists.manage"],"mutable":true,"visible":true},{"permissionName":"5e2cb68f-8a64-4d07-97c2-4819895faaff","displayName":"Acquisitions 7 (Admin)","id":"5e2cb68f-8a64-4d07-97c2-4819895faaff","tags":[],"subPermissions":["ui-finance.acq.unit.assignment.assign","ui-finance.allocations.create","ui-finance.transfers.create","ui-finance.ledger.rollover","ui-finance.acq.unit.assignment.manage","ui-finance.manually-release-encumbrances","ui-finance.fiscal-year.create","ui-finance.fund-budget.create","ui-finance.group.create","ui-finance.ledger.create","ui-finance.fiscal-year.delete","ui-finance.fund-budget.delete","ui-finance.group.delete","ui-finance.ledger.delete","ui-invoice.approve","ui-invoice.acq.unit.assignment.assign","ui-invoice.invoice.create","ui-invoice.invoice.delete","ui-invoice.batchVoucher.download","ui-invoice.acq.unit.assignment.manage","ui-invoice.pay","ui-notes.item.assign-unassign","ui-notes.item.create","ui-notes.item.delete","ui-notes.item.edit","ui-notes.item.view","ui-orders.acq.unit.assignment.assign","ui-orders.order-lines.create","ui-orders.order.create","ui-orders.order-lines.delete","ui-orders.order-lines.edit","ui-orders.order.edit","ui-orders.order.exportCSV","ui-orders.acq.unit.assignment.manage","ui-orders.order.delete","ui-orders.order.reopen","ui-orders.order.unopen","ui-orders.order.updateEncumbrances","ui-orders.order-lines.view","ui-orders.order.view","ui-organizations.acqUnits.assign","ui-organizations.creds.manage","ui-organizations.acqUnits.manage","ui-organizations.create","ui-organizations.delete","ui-receiving.create","ui-receiving.delete","ui-finance.settings.all","ui-invoice.settings.all","ui-orders.settings.all","ui-orders.settings.order-templates.create","ui-orders.settings.order-templates.delete","ui-organizations.settings","ui-receiving.settings","ui-tags.all","ui-users.editperms","ui-users.viewperms"],"mutable":true,"visible":true},{"permissionName":"9974e544-1e88-41dc-9fe8-58830f785644","displayName":"Acquisitions Payments 5 (Staff)","id":"9974e544-1e88-41dc-9fe8-58830f785644","tags":[],"subPermissions":["ui-finance.fiscal-year.view","ui-finance.fund-budget.view","ui-finance.group.view","ui-finance.ledger.view","ui-invoice.approve","ui-invoice.acq.unit.assignment.assign","ui-invoice.invoice.create","ui-invoice.batchVoucher.download","ui-invoice.pay","ui-organizations.acqUnits.assign","ui-organizations.creds.view","ui-organizations.create"],"mutable":true,"visible":true},{"permissionName":"7c36a1cd-f57b-4af6-b9e9-dd271ea16969","displayName":"Access 5 (Staff II)","id":"7c36a1cd-f57b-4af6-b9e9-dd271ea16969","description":"Permissions for staff working in access-related functions (circulation, courses, stacks, etc.)","tags":[],"subPermissions":["ui-checkin.all","ui-checkout.all","ui-checkout.circulation","ui-checkout.viewFeeFines","ui-checkout.viewLoans","ui-checkout.viewRequests","ui-circulation-log.log-event.all","ui-courses.maintain-items","ui-courses.all","ui-courses.read-all","ui-courses.read-add-edit","ui-plugin-create-inventory-records.create","ui-users.manual_charge","ui-users.manual_pay","ui-users.manual_waive","ui-inventory.items.mark-long-missing","ui-inventory.items.mark-restricted","ui-inventory.items.mark-unavailable","ui-inventory.instance.view-staff-suppressed-records","ui-inventory.instance.view","ui-orders.order-lines.view","ui-orders.order.view","ui-requests.all","ui-calendar.view","ui-users.overrideItemBlock","ui-users.overridePatronBlock","ui-users.create","ui-users.feesfines.actions.all","ui-users.patron_blocks","ui-users.editproxies","ui-users.edit","ui-users.viewperms","ui-users.viewproxies","ui-users.viewuserservicepoints","ui-users.view","ui-users.reset.password","ui-users.loans.change-due-date","ui-users.loans.claim-item-returned","ui-users.loans.declare-item-lost","ui-users.loans.declare-claimed-returned-item-as-missing","ui-users.loans.renew","ui-users.loans.renew-override","ui-users.loans.view","ui-users.requests.all"],"mutable":true,"visible":true},{"permissionName":"221ba7cd-c6af-4a76-87b4-02b3f185ae13","displayName":"Cataloging 5 (Staff)","id":"221ba7cd-c6af-4a76-87b4-02b3f185ae13","tags":[],"subPermissions":["ui-plugin-create-inventory-records.create","ui-inventory.single-record-import","ui-inventory.items.mark-in-process-non-requestable","ui-inventory.items.mark-intellectual-item","ui-inventory.items.mark-long-missing","ui-inventory.items.mark-restricted","ui-inventory.items.mark-unavailable","ui-inventory.items.mark-unknown","ui-inventory.items.mark-items-withdrawn","ui-inventory.holdings.move","ui-inventory.item.move","ui-inventory.instance.view-staff-suppressed-records","ui-inventory.instance.edit","ui-inventory.holdings.delete","ui-inventory.item.delete","ui-inventory.item.markasmissing","ui-notes.item.create","ui-notes.item.delete","ui-notes.item.edit","ui-notes.item.view","ui-quick-marc.quick-marc-editor.duplicate","ui-quick-marc.quick-marc-editor.all","ui-tags.all"],"mutable":true,"visible":true},{"permissionName":"18f0ebcc-dced-448a-b554-299c6db9c904","displayName":"View","id":"18f0ebcc-dced-448a-b554-299c6db9c904","description":"For bibliographers, selectors, subject specialists, etc. to view status of materials, including ordering, funds, cataloging, and circulation","tags":[],"subPermissions":["ui-agreements.agreements.view","ui-agreements.resources.view","ui-agreements.platforms.view","ui-courses.read-all","ui-eholdings.app.enabled","ui-eholdings.costperuse.view","ui-erm-comparisons.jobs.view","ui-erm-usage.view","ui-finance.fiscal-year.view","ui-finance.fund-budget.view","ui-finance.group.view","ui-finance.ledger.view","ui-plugin-find-agreement.search","ui-plugin-find-eresource.search","ui-plugin-find-license.search","ui-inventory.instance.view-staff-suppressed-records","ui-inventory.instance.view","ui-invoice.invoice.view","ui-licenses.licenses.view","ui-notes.item.view","ui-orders.order.exportCSV","ui-orders.order-lines.view","ui-orders.order.view","ui-organizations.view","ui-receiving.view","ui-requests.view","ui-tags.view","ui-users.viewproxies","ui-users.viewuserservicepoints","ui-users.view","ui-users.loans.view","ui-users.requests.all"],"mutable":true,"visible":true},{"permissionName":"03778ee7-086e-4508-8a65-ac239d6c65ce","displayName":"E-resources 1 (View only)","id":"03778ee7-086e-4508-8a65-ac239d6c65ce","tags":[],"subPermissions":["ui-agreements.agreements.view","ui-agreements.resources.view","ui-agreements.platforms.view","ui-eholdings.app.enabled","ui-eholdings.costperuse.view","ui-erm-comparisons.jobs.view","ui-erm-usage.view","ui-plugin-find-agreement.search","ui-plugin-find-license.search","ui-licenses.licenses.view"],"mutable":true,"visible":true},{"permissionName":"32ed963e-9a6c-4543-bb68-c89fd2e7bf67","displayName":"Acquisitions 1 (View only)","id":"32ed963e-9a6c-4543-bb68-c89fd2e7bf67","tags":[],"subPermissions":["ui-finance.fiscal-year.view","ui-finance.fund-budget.view","ui-finance.group.view","ui-finance.ledger.view","ui-invoice.invoice.view","ui-notes.item.view","ui-orders.order.exportCSV","ui-orders.order-lines.view","ui-orders.order.view","ui-organizations.view","ui-receiving.view","ui-tags.view"],"mutable":true,"visible":true}]}
